simple_spinner/__init__.py
simple_spinner/spinner.py
simple_spinner-0.1.3.dist-info/METADATA
simple_spinner-0.1.3.dist-info/WHEEL
simple_spinner-0.1.3.dist-info/top_level.txt
simple_spinner-0.1.3.dist-info/RECORD
