Metadata-Version: 2.1
Name: simple-spinner
Version: 0.1.3
Summary: Simple Spinner in python
Home-page: https://github.com/wooy0ng/simple_spinner
Author: wooy0ng
Author-email: yygg9800@naver.com
License: UNKNOWN
Platform: UNKNOWN
Classifier: Programming Language :: Python :: 3
Classifier: License :: OSI Approved :: MIT License
Classifier: Operating System :: OS Independent
Requires-Python: >=3.8
